opts/ArcherAuth.py
opts/ArcherServerClient.py
opts/ContextError.py
opts/SigningError.py
opts/__init__.py
opts/templates/ExecuteSearch.xml
opts/templates/GetReports.xml
opts/templates/GetSearchOptionsByGuid.xml
opts/templates/__init__.py
opts/templates/template.xml
uscis_opts-0.1.4.dist-info/LICENSE
uscis_opts-0.1.4.dist-info/METADATA
uscis_opts-0.1.4.dist-info/WHEEL
uscis_opts-0.1.4.dist-info/top_level.txt
uscis_opts-0.1.4.dist-info/RECORD
