Metadata-Version: 2.1
Name: uscis-opts
Version: 0.1.4
Summary: A python module to simplify RSA Archer API calls.
Author-email: Joshua Davis <Joshua.C.Davis@uscis.dhs.gov>
Project-URL: Homepage, https://git.uscis.dhs.gov/jcdavis1/Archer_API
Project-URL: Bug Tracker, https://git.uscis.dhs.gov/jcdavis1/Archer_API/issues
Classifier: Programming Language :: Python :: 3
Classifier: License :: OSI Approved :: MIT License
Classifier: Operating System :: OS Independent
Requires-Python: >=3.7
License-File: LICENSE
Requires-Dist: pandas >1.0.1
Requires-Dist: requests
